pulumi_kafka/__init__.py
pulumi_kafka/_utilities.py
pulumi_kafka/acl.py
pulumi_kafka/get_topic.py
pulumi_kafka/get_topics.py
pulumi_kafka/outputs.py
pulumi_kafka/provider.py
pulumi_kafka/pulumi-plugin.json
pulumi_kafka/py.typed
pulumi_kafka/quota.py
pulumi_kafka/topic.py
pulumi_kafka/user_scram_credential.py
pulumi_kafka/config/__init__.py
pulumi_kafka/config/__init__.pyi
pulumi_kafka/config/vars.py
pulumi_kafka-3.12.1.dist-info/METADATA
pulumi_kafka-3.12.1.dist-info/WHEEL
pulumi_kafka-3.12.1.dist-info/top_level.txt
pulumi_kafka-3.12.1.dist-info/RECORD
